morteza_pythonpackage/__init__.py
morteza_pythonpackage/morteza_pythonpackage.py
morteza_pythonpackage-1.0.0.dist-info/METADATA
morteza_pythonpackage-1.0.0.dist-info/WHEEL
morteza_pythonpackage-1.0.0.dist-info/top_level.txt
morteza_pythonpackage-1.0.0.dist-info/RECORD
