Metadata-Version: 2.1
Name: morteza_pythonpackage
Version: 1.0.0
Summary: A test package for pydeploy students
Author: mori_cyber
Author-email: moridh1355@gmail.com
